prenzl/__init__.py
prenzl/core.py
prenzl-0.1.5.dist-info/LICENSE
prenzl-0.1.5.dist-info/METADATA
prenzl-0.1.5.dist-info/WHEEL
prenzl-0.1.5.dist-info/top_level.txt
prenzl-0.1.5.dist-info/RECORD
