Metadata-Version: 2.1
Name: prenzl
Version: 0.1.5
Summary: Agent and advanced RAG observability tool in python
Home-page: https://github.com/OptimaLLM/python-sdk
Author: OptimaLLM
Author-email: charlotte.cronjaeger@googlemail.com
Classifier: Programming Language :: Python :: 3
Classifier: License :: OSI Approved :: MIT License
Classifier: Operating System :: OS Independent
Requires-Python: >=3.6
License-File: LICENSE
